dependency_groups/__init__.py
dependency_groups/__main__.py
dependency_groups/_implementation.py
dependency_groups/_lint_dependency_groups.py
dependency_groups/_pip_wrapper.py
dependency_groups/py.typed
dependency_groups-1.2.0.dist-info/entry_points.txt
dependency_groups-1.2.0.dist-info/LICENSE.txt
dependency_groups-1.2.0.dist-info/WHEEL
dependency_groups-1.2.0.dist-info/METADATA
dependency_groups-1.2.0.dist-info/RECORD
