Metadata-Version: 2.1
Name: dependency-groups
Version: 1.2.0
Summary: A tool for resolving PEP 735 Dependency Group data
Keywords: 
Author-email: Stephen Rosen <sirosen0@gmail.com>
Requires-Python: >=3.8
Classifier: Development Status :: 5 - Production/Stable
Classifier: Programming Language :: Python
Classifier: Programming Language :: Python :: 3.8
Classifier: Programming Language :: Python :: 3.9
Classifier: Programming Language :: Python :: 3.10
Classifier: Programming Language :: Python :: 3.11
Classifier: Programming Language :: Python :: 3.12
Classifier: Programming Language :: Python :: 3.13
Classifier: Programming Language :: Python :: Implementation :: CPython
Classifier: Programming Language :: Python :: Implementation :: PyPy
Requires-Dist: packaging
Requires-Dist: tomli;python_version<'3.11'
Project-URL: changelog, https://github.com/sirosen/dependency-groups/blob/main/CHANGELOG.rst
Project-URL: documentation, https://dependency-groups.readthedocs.io/
Project-URL: source, https://github.com/sirosen/dependency-groups
